rerain/__init__.py
rerain/functions/math/__init__.py
rerain/functions/math/math.py
rerain/functions/qr/__init__.py
rerain/functions/qr/qr.py
rerain/functions/sys/__init__.py
rerain/functions/sys/audio.py
rerain/functions/sys/mic.py
rerain/functions/sys/sys.py
rerain/functions/sys/time.py
rerain-1.0.7.dist-info/licenses/LICENSE
rerain-1.0.7.dist-info/METADATA
rerain-1.0.7.dist-info/WHEEL
rerain-1.0.7.dist-info/top_level.txt
rerain-1.0.7.dist-info/RECORD
